Metadata-Version: 1.0
Name: xtalpi-pandas
Version: 0.1.5
Summary: XtalPi Pandas CMD
Home-page: UNKNOWN
Author: Wenzhi Ma
Author-email: wenzhi.ma@xtalpi.com
License: UNKNOWN
Platform: UNKNOWN
